README.md
setup.py
lighthive/__init__.py
lighthive/client.py
lighthive/datastructures.py
lighthive/exceptions.py
lighthive/node_picker.py
lighthive.egg-info/PKG-INFO
lighthive.egg-info/SOURCES.txt
lighthive.egg-info/dependency_links.txt
lighthive.egg-info/requires.txt
lighthive.egg-info/top_level.txt
lighthive/broadcast/__init__.py
lighthive/broadcast/base58.py
lighthive/broadcast/chains.py
lighthive/broadcast/key_objects.py
lighthive/broadcast/transaction_builder.py
lighthive/broadcast/utils.py
lighthive/helpers/__init__.py
lighthive/helpers/account.py
lighthive/helpers/amount.py
lighthive/helpers/event_listener.py