Metadata-Version: 2.1
Name: lighthive
Version: 0.4.3
Summary: A light python client to interact with the HIVE blockchain
Home-page: http://github.com/emre/lighthive
Author: emre yilmaz
Author-email: mail@emreyilmaz.me
License: MIT
Platform: UNKNOWN
Provides-Extra: dev
